bdchecker/__init__.py
bdchecker/__version__.py
bdchecker/checker.py
bdchecker/main.py
bdchecker/command/check.py
bdchecker/command/clean.py
bdchecker/command/gen.py
bdchecker/utils/__init__.py
bdchecker/utils/const_var.py
bdchecker/utils/log_handle.py
bdchecker/utils/singleton.py
bdchecker-0.0.3.dist-info/LICENSE
bdchecker-0.0.3.dist-info/METADATA
bdchecker-0.0.3.dist-info/WHEEL
bdchecker-0.0.3.dist-info/entry_points.txt
bdchecker-0.0.3.dist-info/top_level.txt
bdchecker-0.0.3.dist-info/RECORD
