Metadata-Version: 2.1
Name: bdchecker
Version: 0.0.3
Summary: Backup Data Checker
Author-email: Muggle Wei <mugglewei@gmail.com>
License: The MIT License (MIT)
Project-URL: Homepage, https://github.com/MuggleWei/bdchecker
Project-URL: Bug Tracker, https://github.com/MuggleWei/bdchecker/issues
Keywords: data cold backup,data checker
Classifier: Programming Language :: Python :: 3
Classifier: License :: OSI Approved :: MIT License
Classifier: Operating System :: OS Independent
Requires-Python: >=3.8
License-File: LICENSE
